hebwatch/__init__.py
hebwatch/cities.csv
hebwatch/hebrew-special-numbers-default.yml
hebwatch/hebwatch.py
hebwatch-0.31.dist-info/METADATA
hebwatch-0.31.dist-info/WHEEL
hebwatch-0.31.dist-info/top_level.txt
hebwatch-0.31.dist-info/RECORD
